materialsdb/__init__.py
materialsdb/cache.py
materialsdb/classes.py
materialsdb/config.py
materialsdb/serialiser.py
materialsdb/utils.py
materialsdb/ifc/__init__.py
materialsdb/ifc/material_psets.json
materialsdb/ifc/project_library.py
python_materialsdb-0.0.2.dist-info/LICENSE.md
python_materialsdb-0.0.2.dist-info/METADATA
python_materialsdb-0.0.2.dist-info/WHEEL
python_materialsdb-0.0.2.dist-info/top_level.txt
python_materialsdb-0.0.2.dist-info/RECORD
