Metadata-Version: 2.1
Name: python-materialsdb
Version: 0.0.2
Summary: A library to work with materialsdb.org open standard for building materials.
Home-page: https://github.com/CyrilWaechter/python-materialsdb
Author: Cyril Waechter
Author-email: cyrwae@hotmail.com
License: GPLv3+
Project-URL: Bug Tracker, https://github.com/CyrilWaechter/python-materialsdb/issues
Project-URL: Community, https://community.osarch.org/
Keywords: materials,BIM,ifcopenshell,IFC
Classifier: Programming Language :: Python :: 3
Classifier: License :: OSI Approved :: GNU General Public License v3 or later (GPLv3+)
Classifier: Operating System :: OS Independent
Classifier: Topic :: Software Development :: Libraries :: Python Modules
Classifier: Topic :: Scientific/Engineering
License-File: LICENSE.md
Requires-Dist: lxml
Provides-Extra: ifc
Requires-Dist: ifcopenshell ; extra == 'ifc'
